gpns/__init__.py
gpns/fcm.py
gpns/main.py
gpns-1.1.1.dist-info/LICENSE
gpns-1.1.1.dist-info/METADATA
gpns-1.1.1.dist-info/WHEEL
gpns-1.1.1.dist-info/entry_points.txt
gpns-1.1.1.dist-info/top_level.txt
gpns-1.1.1.dist-info/RECORD
